seismograph/__init__.py
seismograph/load_dataset.py
seismograph/manipulator.py
seismograph/plotter.py
seismograph/study.py
seismograph/util/__init__.py
seismograph/util/docstring.py
seismograph/util/dump.py
seismograph/util/misc.py
seismograph/util/rnastructure.py
seismic_graph-0.0.1.dist-info/LICENSE
seismic_graph-0.0.1.dist-info/METADATA
seismic_graph-0.0.1.dist-info/WHEEL
seismic_graph-0.0.1.dist-info/top_level.txt
seismic_graph-0.0.1.dist-info/RECORD
