Metadata-Version: 2.1
Name: seismic-graph
Version: 0.0.1
Summary: seismograph is a plotting library for SEISMIC
Home-page: https://github.com/rouskinlab/seismograph
Author: Silvi Rouskin Lab
Author-email: silvi@hms.harvard.edu
Requires-Python: >=3.10
License-File: LICENSE
Requires-Dist: plotly
Requires-Dist: numpy
Requires-Dist: pandas
Requires-Dist: scipy
Requires-Dist: matplotlib
Requires-Dist: ipykernel
Requires-Dist: scikit-learn
Requires-Dist: dms-ci
Requires-Dist: custom-inherit
Requires-Dist: tqdm
Requires-Dist: svglib
Requires-Dist: pyyaml
Requires-Dist: pyarrow
Requires-Dist: nbformat >=4.2.0
Requires-Dist: sphinx
Requires-Dist: recommonmark
Requires-Dist: blockdiag
Requires-Dist: sphinx-rtd-theme
Requires-Dist: sphinxcontrib-blockdiag
Requires-Dist: sphinx-panels
Requires-Dist: sphinx-click
